sqlalchemy_odbc4abap/__init__.py
sqlalchemy_odbc4abap/base.py
sqlalchemy_odbc4abap/pyodbc.py
sqlalchemy_odbc4abap/requirements.py
tests/__init__.py
tests/testcases_01.py
sqlalchemy_odbc4abap-0.0.5.dist-info/LICENSE
sqlalchemy_odbc4abap-0.0.5.dist-info/METADATA
sqlalchemy_odbc4abap-0.0.5.dist-info/WHEEL
sqlalchemy_odbc4abap-0.0.5.dist-info/entry_points.txt
sqlalchemy_odbc4abap-0.0.5.dist-info/top_level.txt
sqlalchemy_odbc4abap-0.0.5.dist-info/RECORD
