Metadata-Version: 2.1
Name: sqlalchemy-odbc4abap
Version: 0.0.5
Summary: Connect to S/4HANA CDS View Entities through ODBC.
Author-email: Skye0402 <albrechg@yahoo.com>
License: MIT License
Project-URL: Homepage, https://github.com/skye0402/sqlalchemy-odbc4abap
Keywords: odbc,sap,sqlalchemy,abap,cds
Classifier: License :: OSI Approved :: MIT License
Classifier: Programming Language :: Python
Classifier: Programming Language :: Python :: 3
Requires-Python: >=3.10
License-File: LICENSE
Requires-Dist: sqlalchemy >=2.0.23
Requires-Dist: pyodbc >=5.0.1
Provides-Extra: dev
Requires-Dist: black ; extra == 'dev'
Requires-Dist: bumpver ; extra == 'dev'
Requires-Dist: isort ; extra == 'dev'
Requires-Dist: pip-tools ; extra == 'dev'
Requires-Dist: pytest ; extra == 'dev'
